limecore/cli/__init__.py
limecore/cli/app.py
limecore/cli/app_factory.py
limecore/cli/command.py
limecore_cli-0.1.3.dist-info/LICENSE.txt
limecore_cli-0.1.3.dist-info/METADATA
limecore_cli-0.1.3.dist-info/WHEEL
limecore_cli-0.1.3.dist-info/top_level.txt
limecore_cli-0.1.3.dist-info/RECORD
